greatcirclepaths/__init__.py
greatcirclepaths/gcpsampling.py
greatcirclepaths/gcpwork.py
greatcirclepaths/main.py
greatcirclepaths-1.1.3.dist-info/LICENSE
greatcirclepaths-1.1.3.dist-info/METADATA
greatcirclepaths-1.1.3.dist-info/WHEEL
greatcirclepaths-1.1.3.dist-info/RECORD
