Metadata-Version: 2.1
Name: GreatCirclePaths
Version: 1.1.3
Summary: 
Author: Auggie Marignier
Author-email: augustin.marignier.14@ucl.ac.uk
Requires-Python: >=3.9,<4.0
Classifier: Programming Language :: Python :: 3
Classifier: Programming Language :: Python :: 3.9
Classifier: Programming Language :: Python :: 3.10
Classifier: Programming Language :: Python :: 3.11
Requires-Dist: healpy (>=1.15.2,<2.0.0)
Requires-Dist: matplotlib (>=3.2.2,<4.0.0)
Requires-Dist: numpy (>=1.22.3,<2.0.0)
Requires-Dist: pyssht (>=1.3.2,<2.0.0)
Requires-Dist: scipy (>=1.8.0,<2.0.0)
